[
  { "name": "London" },
  { "name": "Manchester" },
  { "name": "Birmingham" },
  { "name": "Glasgow" },
  { "name": "Liverpool" },
  { "name": "Leeds" },
  { "name": "Newcastle" },
  { "name": "Sheffield" },
  { "name": "Bristol" },
  { "name": "Edinburgh" },
  { "name": "Leicester" },
  { "name": "Coventry" },
  { "name": "Cardiff" },
  { "name": "Belfast" },
  { "name": "Nottingham" },
  { "name": "Bradford" },
  { "name": "Hull" },
  { "name": "Plymouth" },
  { "name": "Stoke-on-Trent" },
  { "name": "Wolverhampton" }
]
